{
"workdata": [
    {
        "施工実績年度": "令和2年度",
        "施工実績データ": [
            {
                "工事発注者": "飛島建設(株)",
                "工事名": "城の前水道管布設工事",
                "工事場所": "大阪府茨木市",
                "完成年月": "令和2年7月 ",
                "写真": ""
            },
            {
                "工事発注者": "(株)淺沼組",
                "工事名": "古江台宅地造成工事",
                "工事場所": "大阪府吹田市",
                "完成年月": "令和2年10月 ",
                "写真": ""
            },
            {
                "工事発注者": "飛島建設(株)",
                "工事名": "クボタ滋賀改修工事",
                "工事場所": "滋賀県湖南市",
                "完成年月": "令和2年12月 ",
                "写真": ""
            },
            {
                "工事発注者": "飛島建設(株)",
                "工事名": "宝塚線雲雀丘等土木工事",
                "工事場所": "兵庫県宝塚市",
                "完成年月": "令和2年12月 ",
                "写真": ""
            },
            {
                "工事発注者": "新誠建設(株)",
                "工事名": "雨水調整池築造工事",
                "工事場所": "兵庫県伊丹市",
                "完成年月": "令和3年3月 ",
                "写真": ""
            },
            {
                "工事発注者": "神鋼興産建設(株)",
                "工事名": "甲陵荘新築工事",
                "工事場所": "兵庫県西宮市",
                "完成年月": "令和3年3月 ",
                "写真": ""
            }
        ]
    },
    {
        "施工実績年度": "令和3年度",
        "施工実績データ": [
            {
                "工事発注者": "兵庫県",
                "工事名": "緊急小規模道路工事",
                "工事場所": "兵庫県伊丹市",
                "完成年月": "令和3年9月 ",
                "写真": ""
            },
            {
                "工事発注者": "世紀東急工業(株)",
                "工事名": "常翔学園新築等工事",
                "工事場所": "大阪府大阪市旭区",
                "完成年月": "令和3年10月 ",
                "写真": ""
            },
            {
                "工事発注者": "(株)ガイアート",
                "工事名": "伊丹隊舎新設等その他工事",
                "工事場所": "兵庫県伊丹市",
                "完成年月": "令和3年12月 ",
                "写真": ""
            },
            {
                "工事発注者": "飛島建設(株)",
                "工事名": "千苅ダム治水活用施設整備工事",
                "工事場所": "兵庫県宝塚市",
                "完成年月": "令和4年3月 ",
                "写真": ""
            },
            {
                "工事発注者": "世紀東急工業(株)",
                "工事名": "中国道橋梁更新工事",
                "工事場所": "大阪府池田市",
                "完成年月": "令和4年3月 ",
                "写真": ""
            }
        ]
    },
    {
        "施工実績年度": "令和4年度",
        "施工実績データ": [
            {
                "工事発注者": "伊丹市",
                "工事名": "市道中央天津線電線共同溝工事",
                "工事場所": "兵庫県伊丹市",
                "完成年月": "令和5年5月",
                "写真": ""
            },
            {
                "工事発注者": "伊丹市上下水道",
                "工事名": "北伊丹地区雨水管渠改築工事",
                "工事場所": "兵庫県伊丹市",
                "完成年月": "令和5年3月",
                "写真": ""
            },
            {
                "工事発注者": "飛鳥建設(株)",
                "工事名": "京都線・千里線淡路駅周辺連続立体交差工事",
                "工事場所": "大阪府大阪市",
                "完成年月": "令和5年6月",
                "写真": ""
            },
            {
                "工事発注者": "飛島建設(株)",
                "工事名": "絹延橋下りホーム改良工事",
                "工事場所": "兵庫県川西市",
                "完成年月": "令和4年12月",
                "写真": ""
            },
            {
                "工事発注者": "(株)ガイアート",
                "工事名": "三国塚口線街路築造工事",
                "工事場所": "大阪府大阪市",
                "完成年月": "令和5年6月",
                "写真": ""
            },
            {
                "工事発注者": "世紀東急工業(株)",
                "工事名": "五宝塚　中国池田IC～宝塚IC間橋梁更新工事",
                "工事場所": "兵庫県宝塚市",
                "完成年月": "令和5年6月",
                "写真": ""
            }
        ]
    }
    
]
}